Workbook

Sheet How To Use
B1: LLM Research Documentation Template
B2: A beginner-friendly log for transparent, reproducible AI research
B4: What this template is for
B5: Purpose | C5: This workbook helps you document every step of your LLM experiments so that you (and others) can understand exactly what you did, why you did it, and what happened. Good documentation is the foundation of trustworthy research.
B6: Who it is for | C6: Beginners and intermediate researchers working with any LLM — cloud APIs (OpenAI, Anthropic, Google, Mistral…), local models (Ollama, LM Studio, llama.cpp…), or open-weight models on HuggingFace.
B7: Core principle | C7: If someone else read your log, could they reproduce your experiment? That is the standard to aim for.
B9: Sheets in this workbook
B10: How To Use | C10: This guide — read first.
B11: Experiment Log | C11: Your main logging sheet. One row = one experiment run. Fill in every column.
B12: Prompt Library | C12: Store and version your prompts here. Reference them from the Experiment Log.
B13: Model Reference | C13: A lookup table of common models, their parameters, and rough pricing.
B14: Summary Dashboard | C14: Auto-calculated stats. Do not edit manually — it updates as you log experiments.
B16: Step-by-step workflow
B17: Step 1 — Before you start | C17: Write your research question in the Experiment Log header. Draft your prompt(s) in the Prompt Library and give each one a version number (e.g. SP-01, UP-01).
B18: Step 2 — Choose your model & settings | C18: Consult the Model Reference sheet to understand the model's parameters. Note the model name, version, temperature, top-p, and seed before running.
B19: Step 3 — Run your experiment | C19: Run the model with your chosen settings. Time-stamp the run. Copy or summarise the output in the Experiment Log.
B20: Step 4 — Evaluate the output | C20: Rate the quality (1–5). Note what worked, what did not. Record any bias, hallucinations, or ethical concerns observed.
B21: Step 5 — Document changes | C21: If you change anything — prompt, temperature, model — log it as a NEW row. Write the rationale ('why did I change this?') and the observed impact.
B22: Step 6 — Review the Dashboard | C22: Check the Summary Dashboard for cost totals, token usage, and quality trends.
B24: Key concepts for beginners
B25: Temperature | C25: Controls randomness. 0 = very predictable (good for structured tasks). 1+ = more creative/varied. Most research should start at 0 or 0.2 for consistency.
B26: Top-p (nucleus sampling) | C26: Limits the pool of words the model picks from. 0.9 means the model only considers the top 90% probability words. Use with temperature, not instead of it.
B27: Top-k | C27: Limits the model to its top K choices at each step. Lower = more focused. Often left at default.
B28: Seed | C28: A number that fixes the random starting point. Two runs with the same seed, prompt, and settings should produce the same output — this is essential for reproducibility. Not all APIs support seeds.
B29: Tokens | C29: The units text is split into. Roughly 1 token ≈ 0.75 English words. APIs charge per token (input and output separately). Context window = the maximum tokens the model can 'see' at once.
B30: System prompt | C30: Instructions given to the model before the user message. Sets tone, role, format, constraints. Changes here can dramatically affect outputs.
B31: Prompt versioning | C31: Give each distinct prompt a version number (e.g. UP-01, UP-02). This lets you trace which prompt produced which result.
B32: Hallucination | C32: When an LLM confidently states something false. Always verify factual claims, especially for research outputs.

Sheet Experiment Log
A1: 🔖 IDENTIFIERS | G1: 🤖 MODEL | L1: ⚙️ PARAMETERS | T1: 💬 PROMPTS & CHANGES | X1: 💰 TOKENS & COST | AC1: 📝 OUTPUT & EVALUATION | AJ1: ⚠️ ETHICS & FLAGS | AN1: 🏷️ TAGS
A2: Run ID | B2: Timestamp (Start) | C2: Duration (mins) | D2: Researcher | E2: Research Question | F2: Iteration Number | G2: Model Name | H2: Model Type (Open/Closed) | I2: Deployment (Cloud/Local) | J2: Provider / Platform | K2: API Version / Endpoint | L2: Temperature | M2: Top-p | N2: Top-k | O2: Max Tokens (Output) | P2: Frequency Penalty | Q2: Presence Penalty | R2: Seed | S2: Stop Sequences | T2: System Prompt Version | U2: User Prompt Version | V2: What Changed (vs. prev.) | W2: Rationale for Change | X2: Input Tokens | Y2: Output Tokens | Z2: Total Tokens | AA2: Cost (USD) | AB2: Cumulative Cost (USD) | AC2: Output Summary (or Paste Full) | AD2: Output File Path / Link | AE2: Expected Output | AF2: Quality Rating (1-5) | AG2: Success Criteria Met? | AH2: Evaluation Notes | AI2: Impact on Research | AJ2: Hallucinations Observed? | AK2: Bias Observed? | AL2: Sensitive Data Used? | AM2: Ethical / Methodological Notes | AN2: Tags / Keywords | AO2: Next Action / Follow-up
A3: R001, R002… | B3: YYYY-MM-DD HH:MM | D3: Your name | G3: gpt-4o-mini, llama3.1:8b… | H3: Open / Closed | I3: Cloud / Local | L3: 0.0 – 2.0 | M3: 0.0 – 1.0 | N3: e.g. 40 | O3: e.g. 2048 | X3: from API response | Y3: from API response | Z3: auto-calculated | AB3: running total | AG3: 1–5 | AH3: Yes / Partial / No | AJ3: Yes / No / Unsure | AL3: Yes / No
A4: R000-A | B4: 2024-06-26 ~09:00 | C4: ~30 | D4: Lauren Coetzee | E4: Can an LLM reliably code historical bead exchange observations from the Time Traveller corpus using a structured codebook (Co-DETECT), and what agreement rate is achievable with systematic prompt engineering? | F4: 0 — Prototype | G4: claude-3-haiku-20240307 | H4: Closed | I4: Cloud | J4: Anthropic | K4: v1 / /v1/messages | L4: default | M4: default | O4: ~1000 | T4: SP-PROTO | U4: UP-PROTO | V4: First prototype | W4: Initial feasibility: LLM + codebook from Drive + XML output | X4: 3000 | Y4: 2000 | Z4: =X4+Y4 -> 5000 | AA4: 0.01 | AB4: =AA4 -> 0.01 | AC4: Tested rows 1–2 from All_entries_beads_shared_RA.xlsx. XML parsed successfully. Proof-of-concept only. | AD4: Google Colab (local) | AE4: XML output parseable; structured extraction feasible. | AF4: 2 | AG4: Partial | AH4: No agreement testing. Scoping run only. | AI4: Established core architecture: LLM + codebook + XML → DataFrame. | AJ4: Not tested | AK4: Not tested | AL4: Yes | AM4: Source corpus contains racialized colonial language. Test sample only. | AN4: prototype, haiku, XML, Drive, beads | AO4: Test with Dropbox for portability. Build session-managed pipeline.
A5: R000-B | B5: 2024-06-26 ~11:00 | C5: ~30 | D5: Lauren Coetzee | E5: Can an LLM reliably code historical bead exchange observations from the Time Traveller corpus using a structured codebook (Co-DETECT), and what agreement rate is achievable with systematic prompt engineering? | F5: 0 — Prototype B | G5: claude-3-haiku-20240307 | H5: Closed | I5: Cloud | J5: Anthropic | K5: v1 / /v1/messages | L5: default | M5: default | O5: ~1000 | T5: SP-PROTO | U5: UP-PROTO | V5: Dropbox variant — data via wget from Dropbox URLs | W5: Testing data portability via shared Dropbox links (beads_extraction_26_June.xlsx + codebook.txt) | X5: 3000 | Y5: 2000 | Z5: =X5+Y5 -> 5000 | AA5: 0.01 | AB5: =AA4+AA5 -> 0.02 | AC5: Same as R000-A but data from Dropbox. XML column named 'xml' vs 'entities' in Drive version — naming inconsistency flagged. | AD5: bead_extraction_results.xlsx (Colab local) | AE5: Dropbox-hosted data loads correctly; XML pipeline portable. | AF5: 2 | AG5: Partial | AH5: Codebook still required Drive fallback. XML column naming inconsistency across notebook versions. | AI5: Confirmed data flexibility. Naming inconsistency → standardise before scale-up. | AJ5: Not tested | AK5: Not tested | AL5: Yes | AM5: Dropbox shared links expose data URL — not suitable long-term for sensitive data. | AN5: prototype, haiku, XML, Dropbox, portability | AO5: Standardise XML column naming. Build session-managed pipeline. Switch to JSON for scale.
A6: R001 | B6: 2024-07-01 09:00 | C6: ~120 | D6: Lauren Coetzee | E6: Can an LLM reliably code historical bead exchange observations from the Time Traveller corpus using a structured codebook (Co-DETECT), and what agreement rate is achievable with systematic prompt engineering? | F6: 1 | G6: claude-3-haiku-20240307 | H6: Closed | I6: Cloud | J6: Anthropic | K6: v1 / /v1/messages | L6: 0.2 | M6: 1.0 | O6: 1000 | P6: 0 | Q6: 0 | S6: </exchange> | T6: SP-01 | U6: UP-01 | V6: First systematic run — no previous version | W6: Haiku for speed/cost. Baseline to identify failure modes before full codebook investment. | X6: 230000 | Y6: 30000 | Z6: =X6+Y6 -> 260000 | AA6: 0.09 | AB6: =AA5+AA6 -> 0.1 | AC6: 100 obs test. ~25% human-AI agreement. Critical failure on 4a_exchange: model coded 'xo' where human found no exchange. | AD6: ⚠ Drive MCP not connected — path: CoDetectBeadAnalysis/run001_haiku_baseline.csv | AE6: Agreement ≥60% on exchange determination. | AF6: 2 | AG6: No | AH6: 25% agreement unacceptable. Haiku too liberal on exchange coding; infers from context not explicit verbs. | AI6: Identified 4a_exchange as highest-impact failure. Triggered full codebook redesign. | AJ6: Yes — hallucinated exchange events | AK6: Yes — colonial framing in outputs | AL6: Yes | AM6: Corpus contains racialized colonial language. Coded variables must be analytically neutral. | AN6: baseline, haiku-3, Co-DETECT, 25-percent, exchange-coding | AO6: Redesign codebook with strict conservative rules. Add decision flowchart for 4a_exchange.
A7: R002 | B7: 2024-07-18 10:00 | C7: ~180 | D7: Lauren Coetzee | E7: Can an LLM reliably code historical bead exchange observations from the Time Traveller corpus using a structured codebook (Co-DETECT), and what agreement rate is achievable with systematic prompt engineering? | F7: 2 | G7: claude-3-haiku-20240307 | H7: Closed | I7: Cloud | J7: Anthropic | K7: v1 / /v1/messages | L7: 0.2 | M7: 1.0 | O7: 1000 | P7: 0 | Q7: 0 | S7: </exchange> | T7: SP-02 | U7: UP-01 | V7: Added strict 3-criterion rule for 4a_exchange | W7: 25% from R001 unacceptable. Conservative alignment required to match human coder standard. | X7: 1150000 | Y7: 150000 | Z7: =X7+Y7 -> 1300000 | AA7: 0.48 | AB7: =AA6+AA7 -> 0.57 | AC7: 500 obs. ~40% agreement. Exchange improved to ~38% but over-correcting on bead characteristics. | AD7: ⚠ Drive MCP not connected — path: CoDetectBeadAnalysis/run002_haiku_conservative.csv | AE7: Agreement ≥60% on 4a_exchange. | AF7: 3 | AG7: Partial | AH7: Improvement but new failure: over-conservative on characteristics. Haiku capability ceiling reached. | AI7: Conservative rules alone insufficient. Edge case expert resolution needed. Upgrade to Sonnet. | AJ7: No | AK7: Yes — residual colonial framing | AL7: Yes | AM7: Over-attribution of exchanges risks replicating colonial barter narratives. | AN7: conservative-rules, haiku-3, v2-codebook, 40-percent | AO7: Upgrade to Sonnet. Develop E1–E5 edge case rules with expert input.
A8: R003 | B8: 2024-08-11 09:30 | C8: ~240 | D8: Lauren Coetzee | E8: Can an LLM reliably code historical bead exchange observations from the Time Traveller corpus using a structured codebook (Co-DETECT), and what agreement rate is achievable with systematic prompt engineering? | F8: 3 | G8: claude-3-sonnet-20240229 | H8: Closed | I8: Cloud | J8: Anthropic | K8: v1 / /v1/messages | L8: 0.2 | M8: 1.0 | O8: 1000 | P8: 0 | Q8: 0 | T8: SP-03 | U8: UP-02 | V8: Model → Sonnet; codebook v3.0 adds E1–E5 expert edge case rules; two-step UP | W8: Haiku hit capability ceiling. Sonnet offers stronger reasoning. Edge cases need explicit resolution. | X8: 1840000 | Y8: 240000 | Z8: =X8+Y8 -> 2080000 | AA8: 9.12 | AB8: =AA7+AA8 -> 9.6 | AC8: 800 obs. ~55% agreement. Exchange determination ~52%. Bead characteristics ~65%. Geographic inconsistent. | AD8: ⚠ Drive MCP not connected — path: CoDetectBeadAnalysis/run003_sonnet_edgecases.csv | AE8: Agreement ≥60% overall; ≥65% on 4a_exchange. | AF8: 3 | AG8: Partial | AH8: 55% = 30pp improvement. Sonnet clearly more capable. Two-step UP improved format alignment. | AI8: 55% justifies final expert validation sprint. Two-step extraction approach becomes standard. | AJ8: No | AK8: Yes — agency attribution in exchange descriptions | AL8: Yes | AM8: Two-step reformatting reduces risk of LLM generating colonial language about African communities. | AN8: sonnet, v3-codebook, edge-cases, 55-percent, two-step | AO8: Expert validation of remaining edge cases. Target v4.0 with all rules locked.
A9: R004 | B9: 2024-08-12 10:00 | C9: ~180 | D9: Lauren Coetzee | E9: Can an LLM reliably code historical bead exchange observations from the Time Traveller corpus using a structured codebook (Co-DETECT), and what agreement rate is achievable with systematic prompt engineering? | F9: 4 | G9: claude-3-5-sonnet-20241022 | H9: Closed | I9: Cloud | J9: Anthropic | K9: v1 / /v1/messages | L9: 0.2 | M9: 1.0 | O9: 1000 | P9: 0 | Q9: 0 | T9: SP-04 | U9: UP-02 | V9: FINAL VALIDATED v4.0 published Zenodo (DOI: 10.5281/zenodo.14550112). P1–P3 preprocessing + E1–E5 locked. | W9: All edge cases systematically resolved. 500-obs validation before production scale-up. | X9: 1150000 | Y9: 150000 | Z9: =X9+Y9 -> 1300000 | AA9: 5.7 | AB9: =AA8+AA9 -> 14.82 | AC9: 500 obs. 73% overall agreement. By category: Exchange 75%, Geographic 72%, Bead characteristics 78%, Cultural 70%. | AD9: ⚠ Drive MCP not connected — path: CoDetectBeadAnalysis/run004_v4_validation.csv | AE9: ≥70% overall agreement across 500 observations. | AF9: 5 | AG9: Yes | AH9: 73% agreement — exceeds 70% threshold. 27% disagreement = ceiling for genuinely ambiguous passages. Codebook archived DOI: 10.5281/zenodo.14550112. | AI9: Production deployment authorised. Co-DETECT validated as reproducible. Zenodo publication enables community use. | AJ9: No | AK9: Partially — cultural variable coding reflects traveller bias | AL9: Yes | AM9: Codebook open on Zenodo. Confidence scores generated; <0.65 flagged. 27% disagreement flagged in all outputs. | AN9: v4.0, validation, 73-percent, Zenodo, Co-DETECT, production-ready | AO9: Deploy at full corpus scale. Use claude-haiku-4-5 for cost efficiency at 27k scale.
A10: R005-S01 | B10: 2025-XX-XX | C10: ~120 | D10: Lauren Coetzee | E10: Can an LLM reliably code historical bead exchange observations from the Time Traveller corpus using a structured codebook (Co-DETECT), and what agreement rate is achievable with systematic prompt engineering? | F10: 5 — Production Session 1 | G10: claude-haiku-4-5-20251001 | H10: Closed | I10: Cloud | J10: Anthropic | K10: v1 / /v1/messages | L10: 0 | M10: 1.0 | O10: 2500 | P10: 0 | Q10: 0 | T10: SP-PROD | U10: UP-PROD | V10: Production scale-up. Expanded 13-field JSON schema. Model → claude-haiku-4-5-20251001 for cost efficiency. | W10: v4.0 validated at 73%. Full corpus requires 14 sessions × 2000 rows. Haiku 4.5 ~15x cheaper than Sonnet. | X10: 4600000 | Y10: 600000 | Z10: =X10+Y10 -> 5200000 | AA10: 3.83 | AB10: =AA9+AA10 -> 9.53 | AC10: Rows 0–1999 coded. JSON output, 13 fields + location enrichments = 29 output columns. Auto-save every 100 rows. | AD10: /content/drive/MyDrive/bead_coding_27k_production/batch_01_rows_0-1999.xlsx | AE10: 2000 rows coded with JSON output matching 29-column schema. | AF10: 4 | AG10: Yes | AH10: Session 1 notebook not available for review but referenced in session management sequence. Temperature=0. | AI10: Marks transition from development to production. Establishes session-managed batching pattern. | AJ10: No | AK10: Residual — flagged entries reviewed manually | AL10: Yes | AM10: 🔴 SECURITY: API key was hard-coded in earlier production scripts (sk-ant-api03-wtLPa4...). Key has been rotated. All new scripts use Colab Secrets (userdata.get) or os.getenv only. | AN10: production, haiku-4-5, session-1, JSON, 13-fields | AO10: Continue sessions 2–14.
A11: R005-S02 | B11: 2025-XX-XX | C11: ~120 | D11: Lauren Coetzee | E11: Can an LLM reliably code historical bead exchange observations from the Time Traveller corpus using a structured codebook (Co-DETECT), and what agreement rate is achievable with systematic prompt engineering? | F11: 5 — Production Session 2 | G11: claude-haiku-4-5-20251001 | H11: Closed | I11: Cloud | J11: Anthropic | K11: v1 / /v1/messages | L11: 0 | M11: 1.0 | O11: 2500 | P11: 0 | Q11: 0 | T11: SP-PROD | U11: UP-PROD | V11: Session 2 fixes: fresh start from row 2000, explicit BATCH_START/END override, improved JSON retry, exponential backoff, per-100-row logging. | W11: Session state corruption caused accidental resumption from wrong rows. Fix: explicit batch range constants. | X11: 4600000 | Y11: 600000 | Z11: =X11+Y11 -> 5200000 | AA11: 3.83 | AB11: =AA10+AA11 -> 7.66 | AC11: Rows 2000–3999 coded. JSON output. Auto-saved every 100 rows. Logs: session_2_processing.log + session_2_errors.log. | AD11: /content/drive/MyDrive/bead_coding_27k_production/batch_02_rows_2000-3999.xlsx | AE11: 2000 rows coded, JSON valid, auto-saved. | AF11: 4 | AG11: Yes | AH11: Session management pattern established. No data loss. Colab URL: https://colab.research.google.com/drive/1YjDTtZxzkvjMcaL6Eyh68j-Bl3u8WwiX | AI11: Session-managed batching pattern confirmed robust. | AJ11: No | AK11: Residual | AL11: Yes | AM11: 🔴 SECURITY: API key was hard-coded in earlier production scripts (sk-ant-api03-wtLPa4...). Key has been rotated. All new scripts use Colab Secrets (userdata.get) or os.getenv only. | AN11: production, haiku-4-5, session-2, rows-2000-3999, JSON | AO11: Continue sessions 3–14.
A12: R005-S03 | B12: 2025-XX-XX | C12: ~120 | D12: Lauren Coetzee | E12: Can an LLM reliably code historical bead exchange observations from the Time Traveller corpus using a structured codebook (Co-DETECT), and what agreement rate is achievable with systematic prompt engineering? | F12: 5 — Production Session 3 | G12: claude-haiku-4-5-20251001 | H12: Closed | I12: Cloud | J12: Anthropic | K12: v1 / /v1/messages | L12: 0 | M12: 1.0 | O12: 2500 | P12: 0 | Q12: 0 | T12: SP-PROD | U12: UP-PROD | V12: Session 3: fresh start row 4000. Same fixes as Session 2. | W12: Continuing production. | X12: 4600000 | Y12: 600000 | Z12: =X12+Y12 -> 5200000 | AA12: 3.83 | AB12: =AA11+AA12 -> 7.66 | AC12: Rows 4000–5999 coded. | AD12: /content/drive/MyDrive/bead_coding_27k_production/batch_03_rows_4000-5999.xlsx | AE12: 2000 rows coded. | AF12: 4 | AG12: Yes | AI12: Consistent quality. | AJ12: No | AK12: Residual | AL12: Yes | AM12: 🔴 SECURITY: API key was hard-coded in earlier production scripts (sk-ant-api03-wtLPa4...). Key has been rotated. All new scripts use Colab Secrets (userdata.get) or os.getenv only. | AN12: production, haiku-4-5, session-3, rows-4000-5999
A13: R005-S04 | B13: 2025-XX-XX | C13: ~150 | D13: Lauren Coetzee | E13: Can an LLM reliably code historical bead exchange observations from the Time Traveller corpus using a structured codebook (Co-DETECT), and what agreement rate is achievable with systematic prompt engineering? | F13: 5 — Production Session 4 (+ Excel fix) | G13: claude-haiku-4-5-20251001 | H13: Closed | I13: Cloud | J13: Anthropic | K13: v1 / /v1/messages | L13: 0 | M13: 1.0 | O13: 2500 | P13: 0 | Q13: 0 | T13: SP-PROD | U13: UP-PROD | V13: CRITICAL BUG FIX: openpyxl crashed on Unicode in cell values ('Southern Africa, xrica cannot be used in worksheets'). Root cause: openpyxl restrictions on Unicode. Fix: sanitize_for_excel() strips problematic chars before writing. | W13: First 1299 rows of Session 4 succeeded; last ~700 crashed. Session 4 re-run with Unicode sanitisation. | X13: 4600000 | Y13: 600000 | Z13: =X13+Y13 -> 5200000 | AA13: 3.83 | AB13: =AA12+AA13 -> 7.66 | AC13: Rows 6000–7999 coded after fix. Smart sanitisation: strips emojis/control chars, preserves accents (é,ñ,ü) + currency (€,£,¥). ~500-600 previously crashed rows recovered. | AD13: /content/drive/MyDrive/bead_coding_27k_production/batch_04_rows_6000-7999.xlsx | AE13: 2000 rows with no openpyxl Unicode errors. | AF13: 4 | AG13: Yes | AH13: Unicode bug affected African place names with diacritics. Smart sanitisation preserves historical spelling accuracy. | AI13: Critical infrastructure fix. Demonstrates importance of testing with real historical corpus data. | AJ13: No | AK13: No | AL13: Yes | AM13: 🔴 SECURITY: API key was hard-coded in earlier production scripts (sk-ant-api03-wtLPa4...). Key has been rotated. All new scripts use Colab Secrets (userdata.get) or os.getenv only. | AN13: production, haiku-4-5, session-4, Excel-fix, Unicode, openpyxl-crash | AO13: Apply smart sanitisation to sessions 5–14 as standard.
A14: R005-S05-S14 | B14: 2025-XX-XX to 2026-01-XX | C14: ~1200 (10 sessions) | D14: Lauren Coetzee | E14: Can an LLM reliably code historical bead exchange observations from the Time Traveller corpus using a structured codebook (Co-DETECT), and what agreement rate is achievable with systematic prompt engineering? | F14: 5 — Production Sessions 5–14 | G14: claude-haiku-4-5-20251001 | H14: Closed | I14: Cloud | J14: Anthropic | K14: v1 / /v1/messages | L14: 0 | M14: 1.0 | O14: 2500 | P14: 0 | Q14: 0 | T14: SP-PROD | U14: UP-PROD | V14: Sessions 5–14: smart Unicode sanitisation standard. S05 8000–9999, S06 10000–11999, S07 12000–13999, S08 14000–15999, S09 16000–17999, S10 18000–19999, S11 20000–21999, S12 22000–23999, S13 24000–25999, S14 26000–27999. | W14: Smart sanitisation as standard after S04 crash. All sessions identical SP-PROD + UP-PROD. | X14: 46000000 | Y14: 6000000 | Z14: =X14+Y14 -> 52000000 | AA14: 38.3 | AB14: =AA13+AA14 -> 42.13 | AC14: Sessions 5–14 complete: rows 8000–27060. 14 batch files. Colab: https://colab.research.google.com/drive/1YjDTtZxzkvjMcaL6Eyh68j-Bl3u8WwiX | AD14: /content/drive/MyDrive/bead_coding_27k_production/batch_05 through batch_14 (10 files) | AE14: All remaining 19,060 rows coded in consistent JSON format. | AF14: 4 | AG14: Yes | AH14: Sessions 5–14 ran without major issues after S04 fix. ~8% flagged for human review. Total: 27,060 obs. | AI14: Complete 27,060-observation corpus coded. 13-field JSON ready for merging. | AJ14: No | AK14: Residual — flagged reviewed manually | AL14: Yes | AM14: 🔴 SECURITY: API key was hard-coded in earlier production scripts (sk-ant-api03-wtLPa4...). Key has been rotated. All new scripts use Colab Secrets (userdata.get) or os.getenv only. | Corpus contains racialized colonial descriptions. | AN14: production, haiku-4-5, sessions-5-14, 27060-obs, JSON, smart-sanitisation | AO14: Merge all 14 batch files. Run metadata merge. Proceed to Murdock join.
A15: R006-A | B15: 2025-08-12 14:35 | C15: ~128 (1,453 rows at 11/min) | D15: Lauren Coetzee | E15: Can an LLM reliably code historical bead exchange observations from the Time Traveller corpus using a structured codebook (Co-DETECT), and what agreement rate is achievable with systematic prompt engineering? | F15: 6A — Munashe validation run (expert edge case notebook) | G15: claude-3-5-sonnet-20241022 | H15: Closed | I15: Cloud | J15: Anthropic | K15: v1 / /v1/messages | L15: default | M15: 1.0 | O15: 1500 | P15: 0 | Q15: 0 | T15: SP-04 | U15: UP-EXP | V15: Expert-validated v4.0 codebook integrated directly in notebook (no external file). Runs on Munashe_Cleaned.xlsx (1,453 rows, 23 columns). 23-variable XML output. Auto-save every 25 rows. Resume capability. | W15: Validate complete v4.0 codebook on separate dataset (Munashe_Cleaned.xlsx) to confirm transferability beyond Time Traveller corpus. | X15: 1160000 | Y15: 580000 | Z15: =X15+Y15 -> 1740000 | AA15: 12.43 | AB15: =AA14+AA15 -> 50.73 | AC15: 1,453 rows coded. 100% success rate (1,453/1,453). Cost: $12.43. Rate: ~11 rows/min. One API error at row 381 recovered on retry. All 23 variables populated. | AD15: /content/drive/MyDrive/bead_annotation/session_2025-08-12_14-35-02/coded_entries_final.xlsx | AE15: 100% successful JSON coding of Munashe_Cleaned.xlsx at v4.0 codebook. | AF15: 5 | AG15: Yes | AH15: 100% success rate across 1,453 rows. Single API 500 error at row 381 recovered gracefully on attempt 2. JSON expansion into columns successful. All 23 variables extracted. | AI15: Confirms v4.0 codebook and pipeline architecture are robust and transferable to new datasets beyond the Time Traveller corpus. | AJ15: No | AK15: Residual — anthropological dataset carries inherent framing | AL15: Yes | AM15: Munashe_Cleaned.xlsx is a different dataset from the main 27k corpus. Source and provenance not documented in notebook. Verify dataset permissions. | AN15: validation, sonnet-3-5, Munashe, 1453-rows, 100-percent-success, expert-codebook, https://colab.research.google.com/github/laurencoetzee001/Beads_Co-detect/blob/main/expert_edgecase_codebook__integrated.ipynb | AO15: Document Munashe dataset provenance. Apply structured dual-column approach (R006-B) to this dataset.
A16: R006-B | B16: 2025-XX-XX (interrupted) | C16: ~5 rows before interrupt | D16: Lauren Coetzee | E16: Can an LLM reliably code historical bead exchange observations from the Time Traveller corpus using a structured codebook (Co-DETECT), and what agreement rate is achievable with systematic prompt engineering? | F16: 6B — Structured dual-column output V3 (interrupted) | G16: claude-sonnet-4-20250514 | H16: Closed | I16: Cloud | J16: Anthropic | K16: v1 / /v1/messages | L16: 0.2 | M16: 1.0 | O16: 3000 | P16: 0 | Q16: 0 | T16: SP-STRUCT | U16: UP-STRUCT | V16: New architecture: XML output with dual-column approach (coded value + descriptive detail per variable = ~49 columns). Data quality pre-check embedded. Temperature 0.2. All_entries_beads_cleaned.xlsx (27,060 rows). | W16: Research need for both statistically analysable coded values AND preserved descriptive richness. Dual columns resolve the quant/qual divide. Model upgraded to claude-sonnet-4-20250514. | X16: 155000 | Y16: 245000 | Z16: =X16+Y16 -> 400000 | AA16: 3.1 | AB16: =AA15+AA16 -> 15.53 | AC16: Keyboard interrupt after ~5 rows. Extracted 49 fields per row. Architecture confirmed working (rows 0–1 showed correct dual-column extraction). Colab URL: github.com/laurencoetzee001/Beads_Co-detect/blob/main output_structure_revised.ipynb | AD16: /content/drive/MyDrive/bead_annotation/structured_session_.../batch_1_rows_0_1.xlsx (incomplete) | AE16: Full 27,060 rows coded with 49-column dual structured output. | AF16: 2 | AG16: Partial | AH16: Architecture validated on 5 rows — 49 fields per row extracted correctly. Interrupted by keyboard. Batch-saving system functional. XML parser works. To be resumed. | AI16: Establishes the production-quality dual-column schema for dissertation analysis. More analytically useful than the 13-field JSON (R005) because it preserves descriptive richness alongside coded values. | AJ16: No | AK16: Not tested at scale | AL16: Yes | AM16: Data quality pre-check (readable/corrupted_ocr/context_page_only/no_bead_content) now embedded as Step 0. Conservative coding at temperature 0.2. | AN16: dual-column, structured-output, sonnet-4, V3, 49-fields, XML, interrupted, GitHub: https://github.com/laurencoetzee001/Beads_Co-detect | AO16: Resume R006-B using batch session management. Process full 27,060 rows. Target: replace R005 JSON with richer dual-column dataset.
A17: R007 | B17: 2026-01-26 09:00 | C17: ~360 | D17: Lauren Coetzee | E17: Can an LLM reliably code historical bead exchange observations from the Time Traveller corpus using a structured codebook (Co-DETECT), and what agreement rate is achievable with systematic prompt engineering? | F17: 7 — Manufacturing & archaeological v5.0 | G17: claude-sonnet-4-20250514 | H17: Closed | I17: Cloud | J17: Anthropic | K17: v1 / /v1/messages | L17: 0.0 | M17: 1.0 | O17: 6000 | P17: 0 | Q17: 0 | T17: SP-V5MFG | U17: UP-V5MFG | V17: Codebook v5.0 (TRAVEL-R / Stellenbosch / Bozen-Bolzano). Adds manufactured_locally and ancient_archaeological to v4.0 rules. JSON output. Data input: manufacturing_rerun_january_2026.xlsx. Model: claude-sonnet-4-20250514. Multiple resume scripts with cross-session batch tracking. | W17: Manufacturing origin and archaeological context required for TRAVEL-R and dissertation manufacturing chapter. Conservative defaults: both new variables default to 'unclear'. | X17: 62238000 | Y17: 8118000 | Z17: =X17+Y17 -> 70356000 | AA17: 308.23 | AB17: =AA16+AA17 -> 311.33 | AC17: Full corpus coded for manufacturing variables. 'unclear' for ~60% (insufficient textual evidence — expected). Archaeological context ~72% confidence. Results: CODED_with_manufacturing_v5_20260126.csv. Multiple resumed sessions. | AD17: /content/drive/MyDrive/Bead_Analysis_v5_Results/CODED_with_manufacturing_v5_20260126.csv | AE17: Reliable coding of manufactured_locally and ancient_archaeological across full corpus. | AF17: 4 | AG17: Yes | AH17: Manufacturing variable: 'yes' coded conservatively (explicit text of local production only). 'ancient_archaeological': 'yes' ONLY for actual excavation/burial context ('excavated at', 'found in tombs'). 'no' for ALL trade narratives including historical patterns and oral traditions. Consistency checks: exchange='no' → price/other_exchanged/process/nature must be N/A. Excel character sanitisation applied throughout. Cross-session batch tracking (glob across all session dirs). | AI17: Enables TRAVEL-R comparative material culture analysis and dissertation manufacturing networks chapter. | AJ17: No | AK17: No | AL17: Yes | AM17: Manufacturing classifications must not reify colonial 'primitive technology' narratives. ancient_archaeological strictly limited to actual excavation context — prevents conflating oral tradition with archaeology. | AN17: manufacturing, archaeological, v5.0, claude-sonnet-4, TRAVEL-R, Stellenbosch, Bozen-Bolzano, JSON, resume-capable | AO17: Merge manufacturing codes with R005 output. Proceed to Murdock ethnographic join.
A18: R008 | B18: 2026-01-28 07:56 | C18: ~30 (pipeline script) | D18: Lauren Coetzee | E18: Can an LLM reliably code historical bead exchange observations from the Time Traveller corpus using a structured codebook (Co-DETECT), and what agreement rate is achievable with systematic prompt engineering? | F18: 8 — Murdock join (no LLM) | G18: Python/Pandas — no LLM | H18: N/A | I18: Local (Colab) | J18: N/A | K18: N/A | L18: N/A | M18: N/A | N18: N/A | O18: N/A | P18: N/A | Q18: N/A | R18: N/A | S18: N/A | T18: N/A | U18: N/A | V18: No LLM. Python/Pandas LEFT JOIN of merged coded dataset with ethnic_beads__version_3__xlsb.xlsx (Murdock Ethnographic Atlas). Join key: snippet_ID = aa. Dataset expands due to one-to-many ethnic group matches. | W18: Murdock classifications required for cross-cultural dissertation analysis. | X18: 0 | Y18: 0 | Z18: =X18+Y18 -> 0 | AA18: 0 | AB18: =AA17+AA18 -> 308.23 | AC18: Final dataset: 36,172 rows × 117 columns. 27,060 unique obs; 17,158 with full Murdock data (63.4%). 5,517 unique ethnic groups. | AD18: /content/drive/MyDrive/Bead_Analysis_v5_Results/FINAL_with_ethnographic_data_20260128_075612.xlsx | AE18: Complete 36k-row analysis-ready dataset with Murdock classifications. | AF18: 5 | AG18: Yes | AH18: Dataset complete. 36,172 rows expanded from 27,060 due to multi-ethnic group obs. File: FINAL_with_ethnographic_data_20260128_075612.xlsx | AI18: Definitive empirical dataset for dissertation beads chapter. Central to C²DH seminar (2026-01-27). | AJ18: N/A | AK18: N/A | AL18: Yes | AM18: Murdock Atlas join introduces ethnographic snapshot risk: 20th-century 'ethnographic present' applied to 16th–19th-century data. This limitation is central to dissertation argument. | AN18: Murdock, ethnographic-join, 36172-rows, 117-columns, analysis-ready, final-dataset | AO18: Proceed to beads chapter analysis. Prepare C²DH seminar presentation. Write Co-DETECT methods paper.
Z19: =IF(AND(X19<>"",Y19<>""),X19+Y19,"") | AB19: =IF(AA19<>"",AA19+AB18,"")
Z20: =IF(AND(X20<>"",Y20<>""),X20+Y20,"") | AB20: =IF(AA20<>"",AA20+AB19,"")
Z21: =IF(AND(X21<>"",Y21<>""),X21+Y21,"") | AB21: =IF(AA21<>"",AA21+AB20,"")
Z22: =IF(AND(X22<>"",Y22<>""),X22+Y22,"") | AB22: =IF(AA22<>"",AA22+AB21,"")
Z23: =IF(AND(X23<>"",Y23<>""),X23+Y23,"") | AB23: =IF(AA23<>"",AA23+AB22,"")
Z24: =IF(AND(X24<>"",Y24<>""),X24+Y24,"") | AB24: =IF(AA24<>"",AA24+AB23,"")
Z25: =IF(AND(X25<>"",Y25<>""),X25+Y25,"") | AB25: =IF(AA25<>"",AA25+AB24,"")
Z26: =IF(AND(X26<>"",Y26<>""),X26+Y26,"") | AB26: =IF(AA26<>"",AA26+AB25,"")
Z27: =IF(AND(X27<>"",Y27<>""),X27+Y27,"") | AB27: =IF(AA27<>"",AA27+AB26,"")
Z28: =IF(AND(X28<>"",Y28<>""),X28+Y28,"") | AB28: =IF(AA28<>"",AA28+AB27,"")
Z29: =IF(AND(X29<>"",Y29<>""),X29+Y29,"") | AB29: =IF(AA29<>"",AA29+AB28,"")
Z30: =IF(AND(X30<>"",Y30<>""),X30+Y30,"") | AB30: =IF(AA30<>"",AA30+AB29,"")
... Z54: =IF(AND(X54<>"",Y54<>""),X54+Y54,"") | AB54: =IF(AA54<>"",AA54+AB53,"")

Sheet Prompt Library
A1: Prompt Library — Version Control for Your Prompts
A2: Version ID | B2: Prompt Type | C2: Date Created | D2: Created By | E2: Prompt Text | F2: Changed From Previous Version | G2: Rationale | H2: Used in Runs | I2: Status
A3: SP-PROTO | B3: System Prompt | C3: 2024-06-26 | D3: Lauren Coetzee | E3: Analyze the following historical text excerpt about bead exchanges and extract specific information related to the beads and their exchange to this codebook {codebook}, use the code of the codebook — more than one answer or codenumber is possible. Get the answers from {text}. Please give an xml output just as in starting with data. | F3: First prototype — no previous | G3: Baseline SP. Codebook injected inline. XML output. Used in R000-A and R000-B. | H3: R000-A, R000-B | I3: Retired
A4: UP-PROTO | B4: User Prompt | C4: 2024-06-26 | D4: Lauren Coetzee | E4: Analyze the following historical text excerpt about bead exchanges and extract specific information related to the beads and their exchange to this codebook {codebook}, use the code of the codebook. Get the answers from {text_page_gp} Please give an xml output just as in starting with data. | F4: First prototype | G4: Baseline UP. Codebook as variable. XML output. Row-by-row. | H4: R000-A, R000-B | I4: Retired
A5: SP-01 | B5: System Prompt | C5: 2024-07-01 | D5: Lauren Coetzee | E5: You are an expert historical coder analyzing texts about precolonial African bead exchange systems from the Time Traveller corpus (1500–1900). Your task is to classify if the text contains meaningful bead-related content and extract key exchange information. Code ONLY what is explicitly stated. Do NOT infer. When uncertain, code as 'unclear' or 'NA'. Output XML format with all required variable tags. | F5: First systematic version — no previous | G5: Baseline SP for Co-DETECT beads pipeline. Establishes role and conservative coding principle. | H5: R001 | I5: Retired
A6: SP-02 | B6: System Prompt | C6: 2024-07-18 | D6: Lauren Coetzee | E6: You are an expert historical coder analyzing texts about precolonial African bead exchange systems. CRITICAL CONSERVATIVE RULE for 4a_exchange: Code 'xo' ONLY when ALL THREE are present: 1. EXPLICIT transaction verb: traded, sold, bought, exchanged, gave for, received for, purchased 2. CLEAR PARTIES: identifiable giver AND receiver 3. COMPLETED ACTION: past tense indicating transaction happened If ANY criterion is missing → code 'no'. Output XML with all required variable tags. | F6: Added strict 3-criterion rule for 4a_exchange | G6: 25% agreement from R001 driven by over-liberal exchange coding. Conservative alignment fix. | H6: R002 | I6: Retired
A7: SP-03 | B7: System Prompt | C7: 2024-08-11 | D7: Lauren Coetzee | E7: You are an expert historical coder analyzing texts about precolonial African bead exchange systems (1500–1900). MANDATORY PREPROCESSING: P1: <50 readable chars → read_entry='NaN', STOP P2: No actual bead content → read_entry='NaN', STOP P3: >60% non-standard chars → read_entry='NaN', STOP EXPERT EDGE CASE RULES: E1 Historical Generalisations → exchange='no' (general pattern, not specific instance) E2 Intangible Exchanges → exchange='xo' (knowledge/services are valid) E3 Observational Contexts → exchange='no' (observation, not transaction) E4 Gift-giving → exchange='xo', nature='social' E5 Equipment Beads → bead_function='aesthetic', exchange='no' Output XML with all variable tags. | F7: Added preprocessing filters P1–P3 and expert edge case rules E1–E5 | G7: Systematic edge case resolution from 800-obs human-expert analysis. | H7: R003 | I7: Retired
A8: SP-04 | B8: System Prompt | C8: 2024-08-12 | D8: Lauren Coetzee | E8: You are an expert historical coder analyzing texts about precolonial African bead exchange systems (1500–1900). === BEAD EXCHANGE CODEBOOK v4.0 (FINAL — Zenodo DOI: 10.5281/zenodo.14550112) === P1–P3 preprocessing filters locked. E1–E5 expert edge case rules locked. 15 VARIABLES: read_entry | 4a_exchange | 2_nature_of_exchange | 4b_beads_exchanged | 4c_exchanged_item | 1a_physical_function | 1b_trade_function | 1c_social_function | 3a_bead_material | 3b_bead_colour | 3c_bead_shape | 3d_bead_size | 5_geographic_location | 5a_ethnic_group | confidence 4a_exchange: 'xo' ONLY with explicit transaction verb + identifiable parties + completed past-tense action. Output ONLY a valid XML block. No preamble. | F8: FINAL VALIDATED v4.0 — all edge cases locked, archived on Zenodo | G8: 73% human-AI agreement. Approved for production deployment. | H8: R004 | I8: Production — Archived on Zenodo
A9: SP-PROD | B9: System Prompt | C9: 2025-XX-XX | D9: Lauren Coetzee | E9: You are a historian analyzing pre-colonial African bead trade records. TASK: Extract ALL 13 structured data fields. Be conservative - require explicit evidence. RESPONSE FORMAT: Return ONLY a JSON object. NO markdown, NO ```json``` tags, NO extra text. JSON STRUCTURE (13 fields): { "1_price_HUMAN": {"status": "yes|no|xo", "amount": "...", "currency": "...", "description": "..."}, "2_size_HUMAN": {"code": 1-6, "description": "..."}, "3_colour_HUMAN": {"codes": [1-14], "description": "..."}, "4_location_HUMAN": {"codes": [1-4], "names": "..."}, "4_location_names_original_spellings": "exact historical spellings", "4_location_context": "Location | Geographic | Strategic | Political", "5_function_HUMAN": {"codes": [1-4], "description": "..."}, "6_origin_of_bead": "geographic origin or null", "7_shape_HUMAN": {"codes": [1-12], "description": "..."}, "8_type_bead_HUMAN": {"codes": [1-14], "description": "..."}, "9_local_name_HUMAN": {"exists": "1|2|null", "names": [...]}, "10_relationship_": {"codes": [1-31], "description": "..."}, "11_units_of_measure": {"type": 1-4, "description": "..."}, "12_bead_ethnic_": ["ethnic group names"], "13_nature_of_exchange": {"code": 1-6, "description": "..."}, "notes": "..." } FIELD CODES: 1_price status: yes=price mentioned, no=not mentioned, xo=exchanged 2_size: 1=large 2=medium 3=small 4=various 5=thin 6=thick 3_colour: 1=red 2=blue 3=white 4=pink 5=coral 6=amber 7=copper 8=green 9=yellow 10=transparent 11=seed glass 12=black 13=multicoloured 14=other 4_location: 1=mountain/hill 2=lake 3=river/waterfall 4=populated place 5_function: 1=jewellery/adornment 2=currency/exchange 3=ceremonial/religious 4=status/gift 7_shape: 1=round 2=tubular 3=square 4=oval 5=oblong 6=punched 7=wound 8=pressed 9=decorative 10=faceted 11=bugle 12=chevron 8_type: 1=glass 2=clay 3=metal 4=stone 5=coral 6=amber 7=bone 8=ivory 9=dried seed 10=ceramic 11=wooden 12=porcelain 13=shell 14=eggshell 10_relationship: 1=wire 2=cloth 3=shells 4=coins 5=livestock 6=iron bars 7=scarabs 8=precious stones 9=antiquities 10=ostrich feathers 11=ebony/ivory 12=salt 13=rubber/gum 14=medicines 15=spices/perfumes 16=wax/seals 17=leather/hides 18=weapons 19=dried food 20=prints/books 21=guns/gunpowder 22=jewellery 23=textiles 24=gold/silver 25=slaves 26=glass objects 27=hardware 28=tobacco 29=musical instruments 30=water 31=alcohol 11_units: 1=string 2=plaited/woven 3=necklace/bracelet/waist 4=other 13_nature: 1=consensual 2=conflictual 3=unspecified 4=competitive/bartering 5=social/gifts 6=uncommercial === CRITICAL EXCHANGE RULES (1_price_HUMAN status / 4a_exchange) === Code 'xo' ONLY when ALL present: ✓ Explicit transaction verb: traded, sold, bought, exchanged, gave, received ✓ Past tense completed action ✓ Clear parties ✓ Specific items ✗ DO NOT code 'xo' for: value descriptions, manufacturing, hypotheticals, general statements, observations, decorative usage === LOCATION EXTRACTION (TWO LAYERS) === Layer 1: Preserve EXACT historical spellings with diacritics: Bontúku, Dahomey, Whydah Layer 2: Geographic + strategic + political context. Format: "Location | Geographic | Strategic | Political" CRITICAL: Return ONLY the JSON object. Use null for missing data. | F9: Complete redesign for production: JSON output (not XML), 13-field expanded schema, two-layer location extraction, 31-item exchange relationship taxonomy, local bead name capture, units of measure. Model: claude-haiku-4-5-20251001. | G9: Production requires: (1) reliable programmatic parsing → JSON cleaner than XML at scale; (2) richer variables for dissertation analysis; (3) cost efficiency at 27k scale. Exchange rules from v4.0 retained. | H9: R005-S01 through R005-S14 | I9: Production — Active
A10: SP-EXP | B10: System Prompt | C10: 2025-08-12 | D10: Lauren Coetzee | E10: You are an expert historical researcher analyzing bead exchange patterns. Use the following expert-validated codebook to analyze this historical text about beads. EXPERT-VALIDATED CODEBOOK v4.0: [Full codebook v4.0 inlined — see Zenodo DOI: 10.5281/zenodo.14550112] CRITICAL REQUIREMENTS: 1. Apply preprocessing data quality rules first (P1–P3) 2. Follow the mandatory decision flowchart 3. Use expert-validated examples for edge cases (E1–E5) 4. When in doubt, be CONSERVATIVE and require explicit evidence 5. Provide a confidence score (0.0-1.0) for your analysis RESPOND WITH PURE JSON ONLY (no text before or after): [23-variable JSON structure including read_entry through 13_notes] | F10: Expert-validated v4.0 codebook inlined directly in notebook (no external file). 23-variable JSON output. claude-3-5-sonnet-20241022. | G10: Validation run on Munashe_Cleaned.xlsx (different dataset from 27k corpus). Tests codebook transferability and confirms 100% success rate on new data. | H10: R006-A | I10: Production — Used in expert_edgecase_codebook__integrated.ipynb; GitHub: https://github.com/laurencoetzee001/Beads_Co-detect
A11: SP-STRUCT | B11: System Prompt | C11: 2025-XX-XX | D11: Lauren Coetzee | E11: STRUCTURED BEAD TRADE CODING CODEBOOK - EXPERT-VALIDATED VERSION V3 ================================================================ Based on highest human-AI agreement rates (July 2025) with edge case improvements. You are analyzing historical texts about pre-colonial African bead trade. Extract information for EVERY variable, providing both CODED VALUES and DESCRIPTIVE DETAILS. DATA QUALITY PRE-CHECK (Step 0): Before coding, check if text: <50 readable chars → data_quality_issue | corrupted OCR → corrupted_ocr | context page → context_page_only | no bead content → no_bead_content CRITICAL INSTRUCTIONS: 1. Answer ALL variables in order 2. Use "none" or "no" if information not present 3. Be CONSERVATIVE — require explicit evidence; do NOT infer 4. Temperature 0.2: be consistent and precise 5. Provide both coded answer AND descriptive detail for each variable 4a_exchange RULES: "xo" ONLY when text explicitly describes beads traded/bartered/sold for something specific "no" for ALL other mentions: manufacturing, value descriptions, adornment, market displays, general demand, ceremonial use, payment systems, historical generalizations, observational contexts SPECIAL CASES: gift-giving with "offered presents" = "xo"; intangible exchanges = "xo"; equipment beads = "no" DUAL COLUMN OUTPUT FORMAT (XML): <analysis> <data_quality>[readable/corrupted_ocr/context_page_only/no_bead_content]</data_quality> <thinking>[analysis process]</thinking> <variables> <var_read_entry>0/1/2/NaN</var_read_entry> <var_read_entry_detail>readability and bead relevance</var_read_entry_detail> ... [all 23 variables × 2 = 46 coded+detail pairs + data_quality + thinking = ~49 fields] <var_4a_exchange>no or xo</var_4a_exchange> <var_4a_exchange_detail>explicit exchange evidence</var_4a_exchange_detail> ... </variables> </analysis> Model: claude-sonnet-4-20250514 | Temperature: 0.2 | Max tokens: 3000 | F11: New dual-column architecture: coded value + descriptive detail per variable = ~49 fields. Data quality pre-check (Step 0). Temperature 0.2. XML output. claude-sonnet-4-20250514. | G11: Addresses limitation of JSON-only approach: preserves both statistically analysable codes AND rich descriptive content in separate columns. Dual columns resolve the quant/qual divide for dissertation analysis. | H11: R006-B | I11: In Progress — interrupted; GitHub: https://github.com/laurencoetzee001/Beads_Co-detect
A12: SP-V5MFG | B12: System Prompt | C12: 2026-01-26 | D12: Lauren Coetzee | E12: You are an expert historical coder analyzing texts about precolonial African bead exchange systems. CRITICAL INSTRUCTIONS: - Code ONLY what is EXPLICITLY stated in the text - Do NOT infer, assume, or interpret beyond what is directly written - When uncertain, be CONSERVATIVE and code as "unclear" or "N/A" - Follow all decision rules strictly PREPROCESSING FILTERS (Apply First): P1: Text < 50 readable characters → read_entry = "NaN", STOP coding P2: Context/title page without bead content → read_entry = "NaN", STOP coding P3: 60%+ non-standard characters → read_entry = "NaN", STOP coding EXPERT DECISION RULES (E1–E5): [same as v4.0] VARIABLES TO CODE (16 total): 1. read_entry: full text OR "NaN" if fails P1-P3 2. exchange: "yes"|"no" 3. bead_function: aesthetic/currency/valuable/spiritual/social_marker/magical (comma-separated) 4. bead_material: glass/stone/metal/organic/mixed (ONLY if explicit) 5. bead_color: exact color terms or N/A 6. bead_shape: round/cylindrical/tubular/disk or exact terms 7. price_of_bead: all pricing info, rates, relative values 8. beads_exchanged: brief description in transaction 9. other_exchanged: what traded for beads 10. process_of_exchange: how exchange occurred 11. ethnic_group: exact names from text 12. nature_of_exchange: "positive"|"conflictual"|"neutral"|"N/A" 13. time_reference: "contemporary"|"historical"|"hypothetical"|"mixed" 14. manufactured_locally: "yes"|"no"|"unclear"|"N/A" (N/A = archaeological only) 15. ancient_archaeological: "yes"|"no"|"unclear" - "yes" ONLY for: "excavated at", "dug up from", "found in tombs", "recovered from burials", "archaeological site" - "no" for: ALL trade narratives, preserved customs, oral traditions, "lost manufacturing art", ANY currency use observation 16. confidence_score: 0.0 to 1.0 OUTPUT FORMAT: Return ONLY valid JSON with all 16 fields. No markdown, no preamble. | F12: Extended v4.0 with manufactured_locally and ancient_archaeological (16 variables). JSON output. claude-sonnet-4-20250514. Multiple resume scripts with cross-session batch tracking. | G12: Manufacturing origin and archaeological context required for TRAVEL-R and dissertation manufacturing chapter. Strict definition of ancient_archaeological prevents conflating oral tradition with actual excavation context. | H12: R007 | I12: Active — Production
A13: SP-05 | B13: System Prompt | C13: 2026-01-26 | D13: Lauren Coetzee | E13: Same as SP-V5MFG above — alternative label used in earlier documentation. | F13: Same as SP-V5MFG | G13: Alias for SP-V5MFG. | H13: R007 | I13: Alias — see SP-V5MFG
... A21: UP-V5MFG | B21: User Prompt | C21: 2026-01-26 | D21: Lauren Coetzee | E21: Analyze this historical text. Extract ALL 16 fields. Return ONLY a JSON object with all 16 fields. No markdown. {text} | F21: Minimal UP for v5.0 manufacturing run. All codebook rules in SP-V5MFG; UP just passes text. | G21: At temperature=0.0, SP rules are followed consistently. Short UP reduces token overhead at scale. | H21: R007 | I21: Active — Production

Sheet Model Reference
A1: Model Reference — Common LLMs, Parameters & Approximate Pricing
A2: Pricing and specifications change frequently. Always verify at the provider's official pricing page before logging costs.
A3: Model Name | B3: Provider | C3: Type (Open/Closed) | D3: Deployment | E3: Context Window (K tokens) | F3: Input Cost ($/1M tokens) | G3: Output Cost ($/1M tokens) | H3: Default Temp. | I3: Seed Support? | J3: Notes
A4: gpt-4o-2024-08-06 | B4: OpenAI | C4: Closed | D4: Cloud | E4: 128 | F4: 2.50 | G4: 10.00 | H4: 1.0 | I4: Yes | J4: Latest GPT-4o checkpoint. Strong reasoning and vision.
A5: gpt-4o-mini | B5: OpenAI | C5: Closed | D5: Cloud | E5: 128 | F5: 0.15 | G5: 0.60 | H5: 1.0 | I5: Yes | J5: Cheaper, faster. Good for high-volume tasks.
A6: o1 | B6: OpenAI | C6: Closed | D6: Cloud | E6: 200 | F6: 15.00 | G6: 60.00 | H6: 1.0 | I6: Yes | J6: Optimised for complex reasoning. Slower.
A7: claude-3-5-sonnet-20241022 | B7: Anthropic | C7: Closed | D7: Cloud | E7: 200 | F7: 3.00 | G7: 15.00 | H7: 1.0 | I7: Yes | J7: Strong at analysis, code, long documents.
A8: claude-3-haiku-20240307 | B8: Anthropic | C8: Closed | D8: Cloud | E8: 200 | F8: 0.25 | G8: 1.25 | H8: 1.0 | I8: Yes | J8: Fast and cheap. Good for classification tasks.
A9: gemini-2.0-flash | B9: Google | C9: Closed | D9: Cloud | E9: 1000 | F9: 0.10 | G9: 0.40 | H9: 1.0 | I9: Yes | J9: Very long context. Good multimodal support.
A10: gemini-1.5-pro | B10: Google | C10: Closed | D10: Cloud | E10: 2000 | F10: 1.25 | G10: 5.00 | H10: 1.0 | I10: Yes | J10: Largest context window. Document-heavy tasks.
A11: mistral-small-latest | B11: Mistral | C11: Closed | D11: Cloud | E11: 32 | F11: 0.10 | G11: 0.30 | H11: 1.0 | I11: Yes | J11: Cost-effective European model.
A12: llama3.1:8b | B12: Meta / Ollama | C12: Open | D12: Local | E12: 128 | F12: Free | G12: Free | H12: 1.0 | I12: Yes | J12: Run locally via Ollama. Good for experimentation.
A13: llama3.1:70b | B13: Meta / Ollama | C13: Open | D13: Local | E13: 128 | F13: Free | G13: Free | H13: 1.0 | I13: Yes | J13: Larger local model. Requires significant GPU VRAM.
A14: llama3.3:70b | B14: Meta / Ollama | C14: Open | D14: Local | E14: 128 | F14: Free | G14: Free | H14: 1.0 | I14: Yes | J14: Updated Llama 3.3 — improved instruction following.
... A19: qwen2.5:14b | B19: Alibaba / Ollama | C19: Open | D19: Local | E19: 128 | F19: Free | G19: Free | H19: 1.0 | I19: Yes | J19: Strong multilingual capabilities.
A20: Prices shown are approximate as of early 2025. Check openai.com/pricing, anthropic.com/pricing, and ai.google.dev/pricing for current rates. Local models are free to run but require suitable hardware (GPU recommended for 7B+ models).
A21: claude-3-haiku-20240307 | B21: Anthropic | C21: Closed | D21: Cloud | E21: 200 | F21: 0.25 | G21: 1.25 | H21: 1.0 | I21: Yes | J21: Used Co-DETECT R001–R002 (beads). Fast, cheap. Hit analytical ceiling for nuanced historical coding. 25%→40% agreement. Retired.
A22: claude-3-sonnet-20240229 | B22: Anthropic | C22: Closed | D22: Cloud | E22: 200 | F22: 3.00 | G22: 15.00 | H22: 1.0 | I22: Yes | J22: Co-DETECT R003 (beads). 55% agreement with v3.0 codebook. Model now retired by Anthropic.
A23: claude-3-5-sonnet-20241022 | B23: Anthropic | C23: Closed | D23: Cloud | E23: 200 | F23: 3.00 | G23: 15.00 | H23: 1.0 | I23: Yes | J23: Co-DETECT R004 (validation) + R006-A (Munashe). 73% agreement with v4.0. R006-A: 1,453 rows at 100% success, $12.43. Codebook DOI: 10.5281/zenodo.14550112.
A24: claude-haiku-4-5-20251001 | B24: Anthropic | C24: Closed | D24: Cloud | E24: 200 | F24: 0.80 | G24: 4.00 | H24: 1.0 | I24: Yes | J24: PRIMARY PRODUCTION MODEL: Co-DETECT 27k run (R005-S01–S14). Temperature=0. JSON output, 13-field schema. ~15x cheaper than Sonnet at 27k scale. Colab: https://colab.research.google.com/drive/1YjDTtZxzkvjMcaL6Eyh68j-Bl3u8WwiX
A25: claude-sonnet-4-20250514 | B25: Anthropic | C25: Closed | D25: Cloud | E25: 200 | F25: 3.00 | G25: 15.00 | H25: 1.0 | I25: Yes | J25: MANUFACTURING + STRUCTURED RUNS: R007 (v5.0 manufacturing, JSON, 16 fields) + R006-B (structured dual-column XML, temperature 0.2). GitHub: https://github.com/laurencoetzee001/Beads_Co-detect

Sheet Summary Dashboard
B1: Summary Dashboard
B2: Auto-calculated from the Experiment Log. Do not edit this sheet.
B4: Experiment Overview
B5: Total runs logged | C5: =COUNTA('Experiment Log'!A4:A54)-COUNTIF('Experiment Log'!A4:A54,"") -> -21
B6: Unique models tested | C6: =SUMPRODUCT(('Experiment Log'!G4:G54<>"")/COUNTIF(IF('Experiment Log'!G4:G54<>"", 'Experiment Log'!G4:G54,"placeholder"),IF('Experiment Log'!G4:G54<>"", 'Experiment Log'!G4:G54,"placeholder"))) -> #DIV/0!
B8: Cost Tracking
B9: Total cost (USD) | C9: =IFERROR(SUM('Experiment Log'!AB4:AB54),0) -> 785.58
B10: Average cost per run (USD) | C10: =IFERROR(AVERAGE(IF('Experiment Log'!AB4:AB54<>"",'Experiment Log'!AB4:AB54)),0) -> 52.372
B12: Token Usage
B13: Total input tokens | C13: =IFERROR(SUM('Experiment Log'!Y4:Y54),0) -> 17917000
B14: Total output tokens | C14: =IFERROR(SUM('Experiment Log'!Z4:Z54),0) -> 150246000
B15: Total tokens (all runs) | C15: =IFERROR(SUM('Experiment Log'!AA4:AA54),0) -> 392.79
B16: Average tokens per run | C16: =IFERROR(AVERAGE(IF('Experiment Log'!AA4:AA54<>"",'Experiment Log'!AA4:AA54)),0) -> 26.186
B18: Quality & Outcomes
B19: Average quality rating (1–5) | C19: =IFERROR(AVERAGEIF('Experiment Log'!AH4:AH54,">0"),0) -> 0
B20: Runs rated 4 or 5 (Good/Excellent) | C20: =COUNTIF('Experiment Log'!AH4:AH54,">=4") -> 0
B21: Runs meeting success criteria (Yes) | C21: =COUNTIF('Experiment Log'!AI4:AI54,"Yes") -> 0
B22: Runs with partial success | C22: =COUNTIF('Experiment Log'!AI4:AI54,"Partial") -> 0
B24: Flags & Ethics
B25: Runs with hallucinations noted (Yes) | C25: =COUNTIF('Experiment Log'!AJ4:AJ54,"Yes") -> 0
B26: Runs with bias observed | C26: =COUNTIF('Experiment Log'!AK4:AK54,"<>"&"")-COUNTIF('Experiment Log'!AK4:AK54,"None observed")-COUNTIF('Experiment Log'!AK4:AK54,"") -> -21
B27: Runs using sensitive data (Yes) | C27: =COUNTIF('Experiment Log'!AL4:AL54,"Yes") -> 15
B29: This dashboard reads directly from your Experiment Log. Add or edit data there, then return here to review totals.
B30: PROJECT: Co-DETECT Beads — Dynamic Economic Institutions in Precolonial Africa, 1500–1900 RESEARCHER: Lauren Coetzee | C²DH, University of Luxembourg | Supervised by Marten Düring GITHUB: https://github.com/laurencoetzee001/Beads_Co-detect CORPUS DATASETS: Main corpus: All_entries_beads_cleaned.xlsx — 27,060 observations (Time Traveller Project) Validation dataset: Munashe_Cleaned.xlsx — 1,453 observations (separate provenance) MODEL PROGRESSION: Development (R001–R003): claude-3-haiku-20240307 → claude-3-sonnet-20240229 Validation (R004, R006-A): claude-3-5-sonnet-20241022 | 73% agreement (v4.0) | 100% success (Munashe) Production 27k (R005): claude-haiku-4-5-20251001 | temperature=0 | JSON | 14 sessions × 2000 rows Manufacturing (R007): claude-sonnet-4-20250514 | temperature=0 | JSON | 16 fields Structured V3 (R006-B): claude-sonnet-4-20250514 | temperature=0.2 | XML dual-column | 49 fields CODEBOOK v4.0 (Zenodo): https://doi.org/10.5281/zenodo.14550112 PRODUCTION COLAB: https://colab.research.google.com/drive/1YjDTtZxzkvjMcaL6Eyh68j-Bl3u8WwiX EXPERT EDGE CASE COLAB: https://colab.research.google.com/github/laurencoetzee001/Beads_Co-detect/blob/main/expert_edgecase_codebook__integrated.ipynb KEY OUTPUT FILES: 27k JSON coded: /content/drive/MyDrive/bead_coding_27k_production/batch_01 through batch_14 Munashe coded: /content/drive/MyDrive/bead_annotation/session_2025-08-12_14-35-02/coded_entries_final.xlsx Manufacturing v5: /content/drive/MyDrive/Bead_Analysis_v5_Results/CODED_with_manufacturing_v5_20260126.csv Final analysis dataset: /content/drive/MyDrive/Bead_Analysis_v5_Results/FINAL_with_ethnographic_data_20260128_075612.xlsx 36,172 rows × 117 columns (after Murdock join) ⚠ GOOGLE DRIVE MCP not connected — connect Drive connector to pull live timestamps and file links. 🔴 SECURITY: API key was hard-coded in earlier scripts — key has been rotated. Use Colab Secrets only.
